README.md
setup.py
calvinmodel/__init__.py
calvinmodel/cbbModels.py
calvinmodel/equilibriumModule.py
calvinmodel.egg-info/PKG-INFO
calvinmodel.egg-info/SOURCES.txt
calvinmodel.egg-info/dependency_links.txt
calvinmodel.egg-info/not-zip-safe
calvinmodel.egg-info/requires.txt
calvinmodel.egg-info/top_level.txt