Metadata-Version: 1.0
Name: calvinmodel
Version: 0.1
Summary: A package with models of the Calvin Cycle
Home-page: https://gitlab.com/ebenhoeh/calvinmodel
Author: Oliver Ebenhoeh
Author-email: oliver.ebenhoeh@hhu.de
License: GPL4
Platform: UNKNOWN
